common/__init__.py
common/azure_utils.py
common/gather_env.py
common/gcp_config_validator.py
common/gcp_monitoring.py
common/gcp_utils.py
common/log.py
common/ncp_security_utils.py
common/ncp_utils.py
common/ncpgov_utils.py
common/progress_decorator.py
common/slack.py
common/utils.py
ic/__init__.py
ic/cli.py
ic/cli_backup.py
ic/commands/__init__.py
ic/commands/config.py
ic/commands/migration.py
ic/commands/security.py
ic/compat/__init__.py
ic/compat/cli.py
ic/compat/common.py
ic/config/__init__.py
ic/config/cleanup.py
ic/config/docs_organizer.py
ic/config/external.py
ic/config/installer.py
ic/config/manager.py
ic/config/migration.py
ic/config/migration_utils.py
ic/config/path_manager.py
ic/config/schema.py
ic/config/secrets.py
ic/config/security.py
ic/core/__init__.py
ic/core/dependency_validator.py
ic/core/logging.py
ic/core/mcp_manager.py
ic/core/platform_discovery.py
ic/core/session.py
ic/core/silence_logging.py
ic/migration/__init__.py
ic/migration/manager.py
ic/migration/post_validation.py
ic/migration/rollback.py
ic/migration/validation.py
ic/platforms/__init__.py
ic/platforms/aws/__init__.py
ic/platforms/aws/cloudfront/__init__.py
ic/platforms/aws/cloudfront/info.py
ic/platforms/aws/codepipeline/__init__.py
ic/platforms/aws/codepipeline/build.py
ic/platforms/aws/codepipeline/deploy.py
ic/platforms/aws/ec2/__init__.py
ic/platforms/aws/ec2/info.py
ic/platforms/aws/ec2/list_tags.py
ic/platforms/aws/ec2/tag_check.py
ic/platforms/aws/ecs/__init__.py
ic/platforms/aws/ecs/info.py
ic/platforms/aws/ecs/service.py
ic/platforms/aws/ecs/task.py
ic/platforms/aws/eks/__init__.py
ic/platforms/aws/eks/addons.py
ic/platforms/aws/eks/fargate.py
ic/platforms/aws/eks/info.py
ic/platforms/aws/eks/nodes.py
ic/platforms/aws/eks/pods.py
ic/platforms/aws/eks/update_config.py
ic/platforms/aws/fargate/__init__.py
ic/platforms/aws/fargate/info.py
ic/platforms/aws/lb/__init__.py
ic/platforms/aws/lb/info.py
ic/platforms/aws/lb/list_tags.py
ic/platforms/aws/lb/tag_check.py
ic_code-1.2.4.dist-info/licenses/LICENSE
ic_code-1.2.4.dist-info/METADATA
ic_code-1.2.4.dist-info/WHEEL
ic_code-1.2.4.dist-info/entry_points.txt
ic_code-1.2.4.dist-info/top_level.txt
ic_code-1.2.4.dist-info/RECORD
