Metadata-Version: 2.4
Name: ic-code
Version: 1.2.4
Summary: Infrastructure CLI tool for managing AWS, Azure, GCP, OCI, NCP, CloudFlare, SSH, and more
Home-page: https://github.com/dgr009/ic
Author: SangYun Kim
Author-email: sykim <cruiser594@gmail.com>
Project-URL: Homepage, https://github.com/dgr009/ic
Project-URL: Bug Reports, https://github.com/dgr009/ic/issues
Project-URL: Source, https://github.com/dgr009/ic
Project-URL: Documentation, https://github.com/dgr009/ic#readme
Keywords: cli,infrastructure,aws,oci,gcp,azure,ncp,naver-cloud,cloudflare,ssh,devops,multi-cloud
Classifier: Development Status :: 5 - Production/Stable
Classifier: Intended Audience :: Developers
Classifier: Intended Audience :: System Administrators
Classifier: License :: OSI Approved :: MIT License
Classifier: Operating System :: OS Independent
Classifier: Programming Language :: Python :: 3
Classifier: Programming Language :: Python :: 3.9
Classifier: Programming Language :: Python :: 3.10
Classifier: Programming Language :: Python :: 3.11
Classifier: Programming Language :: Python :: 3.12
Classifier: Programming Language :: Python :: 3.13
Classifier: Topic :: System :: Systems Administration
Classifier: Topic :: Utilities
Classifier: Topic :: Software Development :: Libraries :: Python Modules
Classifier: Environment :: Console
Requires-Python: >=3.9,<3.15
License-File: LICENSE
Requires-Dist: boto3<2.0.0,>=1.26.0
Requires-Dist: botocore<2.0.0,>=1.29.0
Requires-Dist: oci<3.0.0,>=2.149.0
Requires-Dist: requests<3.0.0,>=2.28.0
Requires-Dist: kubernetes<32.0.0,>=29.0.0
Requires-Dist: awscli<2.0.0,>=1.42.0
Requires-Dist: google-cloud-compute<2.0.0,>=1.36.0
Requires-Dist: google-cloud-container<3.0.0,>=2.44.0
Requires-Dist: google-cloud-storage<3.0.0,>=2.18.0
Requires-Dist: google-cloud-functions<2.0.0,>=1.16.0
Requires-Dist: google-cloud-run<1.0.0,>=0.11.0
Requires-Dist: google-cloud-billing<2.0.0,>=1.13.0
Requires-Dist: google-cloud-resource-manager<2.0.0,>=1.12.0
Requires-Dist: google-auth<3.0.0,>=2.29.0
Requires-Dist: google-auth-oauthlib<2.0.0,>=1.2.0
Requires-Dist: google-auth-httplib2<1.0.0,>=0.2.0
Requires-Dist: azure-identity<2.0.0,>=1.15.0
Requires-Dist: azure-mgmt-compute<32.0.0,>=29.0.0
Requires-Dist: azure-mgmt-network<27.0.0,>=24.0.0
Requires-Dist: azure-mgmt-containerinstance<11.0.0,>=10.1.0
Requires-Dist: azure-mgmt-containerservice<31.0.0,>=28.0.0
Requires-Dist: azure-mgmt-storage<22.0.0,>=21.1.0
Requires-Dist: azure-mgmt-sql<4.0.0,>=3.0.1
Requires-Dist: azure-mgmt-rdbms<11.0.0,>=10.1.0
Requires-Dist: azure-mgmt-eventhub<11.0.0,>=10.1.0
Requires-Dist: azure-mgmt-resource<25.0.0,>=22.0.0
Requires-Dist: azure-mgmt-subscription<4.0.0,>=3.1.1
Requires-Dist: paramiko<5.0.0,>=2.11.0
Requires-Dist: netifaces<1.0.0,>=0.11.0
Requires-Dist: rich<15.0.0,>=12.0.0
Requires-Dist: InquirerPy<1.0.0,>=0.3.4
Requires-Dist: tqdm<5.0.0,>=4.67.0
Requires-Dist: python-dotenv<2.0.0,>=0.19.0
Requires-Dist: python-dateutil<3.0.0,>=2.8.0
Requires-Dist: PyYAML<8.0.0,>=6.0
Requires-Dist: click<9.0.0,>=8.0.0
Requires-Dist: docutils<1.0.0,>=0.19
Requires-Dist: invoke<3.0.0,>=2.2.0
Requires-Dist: jsonschema<5.0.0,>=4.23.0
Requires-Dist: cryptography<50.0.0,>=3.4.8
Requires-Dist: watchdog<6.0.0,>=3.0.0
Requires-Dist: cerberus<2.0.0,>=1.3.4
Requires-Dist: pydantic<3.0.0,>=2.0.0
Requires-Dist: packaging<25.0,>=21.0
Requires-Dist: setuptools<75.0,>=61.0
Provides-Extra: dev
Requires-Dist: pytest<9.0.0,>=7.0.0; extra == "dev"
Requires-Dist: pytest-cov<6.0.0,>=4.0.0; extra == "dev"
Requires-Dist: black<25.0.0,>=22.0.0; extra == "dev"
Requires-Dist: flake8<8.0.0,>=5.0.0; extra == "dev"
Requires-Dist: mypy<2.0.0,>=1.0.0; extra == "dev"
Requires-Dist: pre-commit<4.0.0,>=2.20.0; extra == "dev"
Dynamic: author
Dynamic: home-page
Dynamic: license-file
Dynamic: requires-python
